{"eventHeader":{"eventIdentifier":"b0b5e9c1-3f97-4fa3-ab33-5caa3b442d1c","eventType":"MDM-Contract","MajorSchemaVersion":1,"MinorSchemaVersion":0,"eventDateTime":"2025-09-11T11:18:44.239+08:00"},"keys":[{"keyField":"contractIdentifier","keyField":"6982391060"}],"payload":{"contractIdentifier":{"operation":"INSERT","newValue":"6982391060"},"sourceSystemIdentifier":{"operation":"INSERT","newValue":"COH"},"contractStartDateTime":{"operation":"INSERT","newValue":"2018-03-24T16:26:45.000+08:00"},"contractTitle":{"operation":"INSERT","newValue":[{"contractTitleLineType":"lgl_ttl_ln_1","contractTitleLine":"Tiffany Riley"},{"contractTitleLineType":"lgl_ttl_ln_2","contractTitleLine":"Matthew Davies"}]},"taxIdentifier":{"operation":"INSERT","newValue":{"taxIdType":"EIN","taxId":"ZLCK91795330413525"}},"contractBranchCode":{"operation":"INSERT","newValue":"ACXMGBA5"},"contractCountry":{"operation":"INSERT","newValue":"Mexico"},"partyRelations":[{"partyIdentifier":{"operation":"INSERT","newValue":"9823462810"},"partyRelationshipType":{"operation":"INSERT","newValue":"F-N"},"partyRelationStartDateTime":{"operation":"INSERT","newValue":"2019-07-29T08:51:32.000+08:00"},"col4":{"operation":"INSERT","newValue":{"addressLine1":"45229 Drake Route","addressLine2":"13306 Corey Point","addressCity":"Shanefort","addressPostalCode":"77163","addressCountry":"Canada","addressStartDate":"2019-02-26"}}}]}}
{"eventHeader":{"eventIdentifier":"41b855a4-658e-4259-b46d-73ec06924062","eventType":"MDM-Contract","MajorSchemaVersion":1,"MinorSchemaVersion":0,"eventDateTime":"2025-09-11T11:18:44.239+08:00"},"keys":[{"keyField":"contractIdentifier","keyField":"6982391061"}],"payload":{"contractIdentifier":{"operation":"INSERT","newValue":"6982391061"},"sourceSystemIdentifier":{"operation":"INSERT","newValue":"ADS"},"contractStartDateTime":{"operation":"INSERT","newValue":"2018-07-19T13:54:49.000+08:00"},"contractTitle":{"operation":"INSERT","newValue":[{"contractTitleLineType":"lgl_ttl_ln_1","contractTitleLine":"Garcia and Sons"},{"contractTitleLineType":"lgl_ttl_ln_2","contractTitleLine":"Taylor Guzman"}]},"taxIdentifier":{"operation":"INSERT","newValue":{"taxIdType":"SSP","taxId":"CADU39916151090321"}},"contractBranchCode":{"operation":"INSERT","newValue":"SHJFGBML"},"contractCountry":{"operation":"INSERT","newValue":"United States"},"partyRelations":[{"partyIdentifier":{"operation":"INSERT","newValue":"9823462811"},"partyRelationshipType":{"operation":"INSERT","newValue":"F-N"},"partyRelationStartDateTime":{"operation":"INSERT","newValue":"2018-08-31T07:57:22.000+08:00"},"col4":{"operation":"INSERT","newValue":{"addressLine1":"361 Robinson Green","addressLine2":"3511 Rebecca Mission","addressCity":"North Tyler","addressPostalCode":"34118","addressCountry":"Canada","addressStartDate":"2018-01-28"}}}]}}
{"eventHeader":{"eventIdentifier":"7e656720-a906-4d16-bd61-12b7f829df08","eventType":"MDM-Contract","MajorSchemaVersion":1,"MinorSchemaVersion":0,"eventDateTime":"2025-09-11T11:18:44.239+08:00"},"keys":[{"keyField":"contractIdentifier","keyField":"6982391062"}],"payload":{"contractIdentifier":{"operation":"INSERT","newValue":"6982391062"},"sourceSystemIdentifier":{"operation":"INSERT","newValue":"CML"},"contractStartDateTime":{"operation":"INSERT","newValue":"2017-09-24T10:44:17.000+08:00"},"contractTitle":{"operation":"INSERT","newValue":[{"contractTitleLineType":"lgl_ttl_ln_1","contractTitleLine":"Theresa Mays"}]},"taxIdentifier":{"operation":"INSERT","newValue":{"taxIdType":"CPR","taxId":"WTUP76582369402245"}},"contractBranchCode":{"operation":"INSERT","newValue":"XCVKGB49"},"contractCountry":{"operation":"INSERT","newValue":"Canada"},"partyRelations":[{"partyIdentifier":{"operation":"INSERT","newValue":"9823462812"},"partyRelationshipType":{"operation":"INSERT","newValue":"F-N"},"partyRelationStartDateTime":{"operation":"INSERT","newValue":"2018-08-25T18:20:29.000+08:00"},"col4":{"operation":"INSERT","newValue":{"addressLine1":"039 Daniel Mount","addressLine2":"8219 Hernandez Lodge Suite 875","addressCity":"Boltonborough","addressPostalCode":"71648","addressCountry":"Mexico","addressStartDate":"2018-12-07"}}}]}}
{"eventHeader":{"eventIdentifier":"42a9815d-a4bb-4ecf-a086-ce6049ca93a8","eventType":"MDM-Contract","MajorSchemaVersion":1,"MinorSchemaVersion":0,"eventDateTime":"2025-09-11T11:18:44.239+08:00"},"keys":[{"keyField":"contractIdentifier","keyField":"6982391063"}],"payload":{"contractIdentifier":{"operation":"INSERT","newValue":"6982391063"},"sourceSystemIdentifier":{"operation":"INSERT","newValue":"ADS"},"contractStartDateTime":{"operation":"INSERT","newValue":"2019-02-15T12:16:10.000+08:00"},"contractTitle":{"operation":"INSERT","newValue":[{"contractTitleLineType":"lgl_ttl_ln_1","contractTitleLine":"Christopher Moreno"}]},"taxIdentifier":{"operation":"INSERT","newValue":{"taxIdType":"CPR","taxId":"APVN98456428071508"}},"contractBranchCode":{"operation":"INSERT","newValue":"KRGZGB9S"},"contractCountry":{"operation":"INSERT","newValue":"Canada"},"partyRelations":[{"partyIdentifier":{"operation":"INSERT","newValue":"9823462813"},"partyRelationshipType":{"operation":"INSERT","newValue":"F-N"},"partyRelationStartDateTime":{"operation":"INSERT","newValue":"2018-05-11T09:53:28.000+08:00"},"col4":{"operation":"INSERT","newValue":{"addressLine1":"05550 Nancy Rapids","addressLine2":"9471 Zachary Canyon","addressCity":"East Davidport","addressPostalCode":"2504","addressCountry":"United States","addressStartDate":"2019-04-02"}}}]}}
{"eventHeader":{"eventIdentifier":"e7d1a5d5-291b-437f-91d2-41ccffc3b60d","eventType":"MDM-Contract","MajorSchemaVersion":1,"MinorSchemaVersion":0,"eventDateTime":"2025-09-11T11:18:44.239+08:00"},"keys":[{"keyField":"contractIdentifier","keyField":"6982391064"}],"payload":{"contractIdentifier":{"operation":"INSERT","newValue":"6982391064"},"sourceSystemIdentifier":{"operation":"INSERT","newValue":"ADS"},"contractStartDateTime":{"operation":"INSERT","newValue":"2018-03-28T18:17:43.000+08:00"},"contractTitle":{"operation":"INSERT","newValue":[{"contractTitleLineType":"lgl_ttl_ln_1","contractTitleLine":"Allen Group"}]},"taxIdentifier":{"operation":"INSERT","newValue":{"taxIdType":"CPR","taxId":"WJMX61093523376960"}},"contractBranchCode":{"operation":"INSERT","newValue":"OCCKGB65"},"contractCountry":{"operation":"INSERT","newValue":"Canada"},"partyRelations":[{"partyIdentifier":{"operation":"INSERT","newValue":"9823462814"},"partyRelationshipType":{"operation":"INSERT","newValue":"F-N"},"partyRelationStartDateTime":{"operation":"INSERT","newValue":"2019-06-06T16:48:12.000+08:00"},"col4":{"operation":"INSERT","newValue":{"addressLine1":"5227 Wagner Pines","addressLine2":"189 Julie Throughway","addressCity":"West Amanda","addressPostalCode":"78962","addressCountry":"Canada","addressStartDate":"2018-07-11"}}}]}}
{"eventHeader":{"eventIdentifier":"5268e1c0-d096-478a-a3da-226ce014978f","eventType":"MDM-Contract","MajorSchemaVersion":1,"MinorSchemaVersion":0,"eventDateTime":"2025-09-11T11:18:44.239+08:00"},"keys":[{"keyField":"contractIdentifier","keyField":"6982391065"}],"payload":{"contractIdentifier":{"operation":"INSERT","newValue":"6982391065"},"sourceSystemIdentifier":{"operation":"INSERT","newValue":"COR"},"contractStartDateTime":{"operation":"INSERT","newValue":"2018-07-01T01:03:19.000+08:00"},"contractTitle":{"operation":"INSERT","newValue":[{"contractTitleLineType":"lgl_ttl_ln_1","contractTitleLine":"Austin Miles"}]},"taxIdentifier":{"operation":"INSERT","newValue":{"taxIdType":"EIN","taxId":"TYAB75470638120665"}},"contractBranchCode":{"operation":"INSERT","newValue":"XCVKGB49"},"contractCountry":{"operation":"INSERT","newValue":"Canada"},"partyRelations":[{"partyIdentifier":{"operation":"INSERT","newValue":"9823462815"},"partyRelationshipType":{"operation":"INSERT","newValue":"F-N"},"partyRelationStartDateTime":{"operation":"INSERT","newValue":"2019-05-04T07:42:37.000+08:00"},"col4":{"operation":"INSERT","newValue":{"addressLine1":"6993 Diane Alley","addressLine2":"8945 Trevor Greens","addressCity":"Kendrafurt","addressPostalCode":"50790","addressCountry":"United States","addressStartDate":"2017-10-08"}}}]}}
{"eventHeader":{"eventIdentifier":"dd82314c-2a77-4cbf-8900-ea0920f2de9a","eventType":"MDM-Contract","MajorSchemaVersion":1,"MinorSchemaVersion":0,"eventDateTime":"2025-09-11T11:18:44.239+08:00"},"keys":[{"keyField":"contractIdentifier","keyField":"6982391066"}],"payload":{"contractIdentifier":{"operation":"INSERT","newValue":"6982391066"},"sourceSystemIdentifier":{"operation":"INSERT","newValue":"BDL"},"contractStartDateTime":{"operation":"INSERT","newValue":"2017-08-25T05:30:00.000+08:00"},"contractTitle":{"operation":"INSERT","newValue":[{"contractTitleLineType":"lgl_ttl_ln_1","contractTitleLine":"Miss Lisa Lee"}]},"taxIdentifier":{"operation":"INSERT","newValue":{"taxIdType":"SSP","taxId":"WFDP61047142851240"}},"contractBranchCode":{"operation":"INSERT","newValue":"CVYEGBJC"},"contractCountry":{"operation":"INSERT","newValue":"United States"},"partyRelations":[{"partyIdentifier":{"operation":"INSERT","newValue":"9823462816"},"partyRelationshipType":{"operation":"INSERT","newValue":"F-N"},"partyRelationStartDateTime":{"operation":"INSERT","newValue":"2019-05-15T13:09:29.000+08:00"},"col4":{"operation":"INSERT","newValue":{"addressLine1":"23450 Timothy Divide","addressLine2":"125 Johnson Mountain Suite 701","addressCity":"Osbornetown","addressPostalCode":"4756","addressCountry":"Canada","addressStartDate":"2018-11-28"}}}]}}
{"eventHeader":{"eventIdentifier":"c63ba3b4-6c5a-4271-9e0b-bc2f35c1a4dd","eventType":"MDM-Contract","MajorSchemaVersion":1,"MinorSchemaVersion":0,"eventDateTime":"2025-09-11T11:18:44.239+08:00"},"keys":[{"keyField":"contractIdentifier","keyField":"6982391067"}],"payload":{"contractIdentifier":{"operation":"INSERT","newValue":"6982391067"},"sourceSystemIdentifier":{"operation":"INSERT","newValue":"BDL"},"contractStartDateTime":{"operation":"INSERT","newValue":"2018-08-29T19:48:59.000+08:00"},"contractTitle":{"operation":"INSERT","newValue":[{"contractTitleLineType":"lgl_ttl_ln_1","contractTitleLine":"Acosta Inc"},{"contractTitleLineType":"lgl_ttl_ln_2","contractTitleLine":"David Walker"}]},"taxIdentifier":{"operation":"INSERT","newValue":{"taxIdType":"SSP","taxId":"UJLN20870916345792"}},"contractBranchCode":{"operation":"INSERT","newValue":"WZTEGBTG"},"contractCountry":{"operation":"INSERT","newValue":"Canada"},"partyRelations":[{"partyIdentifier":{"operation":"INSERT","newValue":"9823462817"},"partyRelationshipType":{"operation":"INSERT","newValue":"F-N"},"partyRelationStartDateTime":{"operation":"INSERT","newValue":"2018-05-16T12:23:04.000+08:00"},"col4":{"operation":"INSERT","newValue":{"addressLine1":"251 Lee Tunnel","addressLine2":"09795 Tara Station Suite 264","addressCity":"New Michelleborough","addressPostalCode":"5505","addressCountry":"United States","addressStartDate":"2019-04-20"}}},{"partyIdentifier":{"operation":"INSERT","newValue":"9823462820"},"partyRelationshipType":{"operation":"INSERT","newValue":"F-S"},"partyRelationStartDateTime":{"operation":"INSERT","newValue":"2017-11-20T16:48:05.000+08:00"}},{"partyIdentifier":{"operation":"INSERT","newValue":"9823462821"},"partyRelationshipType":{"operation":"INSERT","newValue":"F-S"},"partyRelationStartDateTime":{"operation":"INSERT","newValue":"2018-07-19T21:26:57.000+08:00"}}]}}
{"eventHeader":{"eventIdentifier":"291fae08-b07e-405d-be99-267aa3709e54","eventType":"MDM-Contract","MajorSchemaVersion":1,"MinorSchemaVersion":0,"eventDateTime":"2025-09-11T11:18:44.239+08:00"},"keys":[{"keyField":"contractIdentifier","keyField":"6982391068"}],"payload":{"contractIdentifier":{"operation":"INSERT","newValue":"6982391068"},"sourceSystemIdentifier":{"operation":"INSERT","newValue":"BDL"},"contractStartDateTime":{"operation":"INSERT","newValue":"2018-05-11T17:54:57.000+08:00"},"contractTitle":{"operation":"INSERT","newValue":[{"contractTitleLineType":"lgl_ttl_ln_1","contractTitleLine":"Amanda Martin"}]},"taxIdentifier":{"operation":"INSERT","newValue":{"taxIdType":"EIN","taxId":"JDPX30428146546118"}},"contractBranchCode":{"operation":"INSERT","newValue":"ACXMGBA5"},"contractCountry":{"operation":"INSERT","newValue":"Mexico"},"partyRelations":[{"partyIdentifier":{"operation":"INSERT","newValue":"9823462818"},"partyRelationshipType":{"operation":"INSERT","newValue":"F-N"},"partyRelationStartDateTime":{"operation":"INSERT","newValue":"2017-11-27T03:50:12.000+08:00"},"col4":{"operation":"INSERT","newValue":{"addressLine1":"7537 Clarke Club","addressLine2":"74089 Jerry Trail","addressCity":"Hunterville","addressPostalCode":"19596","addressCountry":"United States","addressStartDate":"2018-07-17"}}}]}}
